funboost/README.md
funboost/__init__.py
funboost/__init__old.py
funboost/__main__.py
funboost/constant.py
funboost/funboost_config_deafult.py
funboost/set_frame_config.py
funboost/assist/__init__.py
funboost/assist/celery_helper.py
funboost/assist/dramatiq_helper.py
funboost/assist/faststream_helper.py
funboost/assist/huey_helper.py
funboost/assist/rocketry_helper.py
funboost/assist/rq_helper.py
funboost/assist/rq_windows_worker.py
funboost/assist/taskiq_helper.py
funboost/beggar_version_implementation/README.md
funboost/beggar_version_implementation/__init__.py
funboost/beggar_version_implementation/beggar_redis_consumer.py
funboost/concurrent_pool/__init__.py
funboost/concurrent_pool/async_helper.py
funboost/concurrent_pool/async_pool_executor.py
funboost/concurrent_pool/base_pool_type.py
funboost/concurrent_pool/bounded_processpoolexcutor_gt_py37.py
funboost/concurrent_pool/bounded_processpoolexcutor_py36.py
funboost/concurrent_pool/bounded_threadpoolexcutor.py
funboost/concurrent_pool/concurrent_pool_with_multi_process.py
funboost/concurrent_pool/custom_evenlet_pool_executor.py
funboost/concurrent_pool/custom_gevent_pool_executor.py
funboost/concurrent_pool/custom_threadpool_executor.py
funboost/concurrent_pool/custom_threadpool_executor000.py
funboost/concurrent_pool/fixed_thread_pool.py
funboost/concurrent_pool/flexible_thread_pool.py
funboost/concurrent_pool/pool_commons.py
funboost/concurrent_pool/readme.md
funboost/concurrent_pool/single_thread_executor.py
funboost/concurrent_pool/backup/__init__.py
funboost/concurrent_pool/backup/aio_pool1029.py
funboost/concurrent_pool/backup/aio_pool20251028.py
funboost/concurrent_pool/backup/async_pool_executor0223.py
funboost/concurrent_pool/backup/async_pool_executor_back.py
funboost/concurrent_pool/backup/async_pool_executor_janus.py
funboost/concurrent_pool/backup/grok_async_pool.py
funboost/consumers/__init__.py
funboost/consumers/base_consumer.py
funboost/consumers/celery_consumer.py
funboost-53.8.dist-info/METADATA
funboost-53.8.dist-info/WHEEL
funboost-53.8.dist-info/entry_points.txt
funboost-53.8.dist-info/top_level.txt
funboost-53.8.dist-info/RECORD
