Metadata-Version: 2.4
Name: funboost
Version: 53.8
Summary: pip install funboost，python全功能分布式函数调度框架,funboost的功能是全面性重量级，用户能想得到的功能99%全都有;funboost的使用方式是轻量级，只有@boost一行代码需要写。支持python所有类型的并发模式和一切知名消息队列中间件，支持如 celery dramatiq等框架整体作为funboost中间件，python函数加速器，框架包罗万象，用户能想到的控制功能全都有。一统编程思维，兼容50% python业务场景，适用范围广。只需要一行代码即可分布式执行python一切函数，funboost web manager 方便查看和管理消费函数；99%用过funboost的pythoner 感受是　简易 方便 强劲 强大，相见恨晚 
Home-page: https://github.com/ydf0509/funboost
Author: bfzs
Author-email: ydf0509@sohu.com
Maintainer: ydf
Maintainer-email: ydf0509@sohu.com
License: BSD-3-Clause
Keywords: funboost,distributed-framework,function-scheduling,rabbitmq,rocketmq,kafka,nsq,redis,disk,sqlachemy,consume-confirm,timing,task-scheduling,apscheduler,pulsar,mqtt,kombu,的,celery,框架,分布式调度
Platform: all
Classifier: Development Status :: 4 - Beta
Classifier: Operating System :: OS Independent
Classifier: Intended Audience :: Developers
Classifier: Programming Language :: Python
Classifier: Programming Language :: Python :: Implementation
Classifier: Programming Language :: Python :: 3
Classifier: Programming Language :: Python :: 3.7
Classifier: Programming Language :: Python :: 3.8
Classifier: Programming Language :: Python :: 3.9
Classifier: Programming Language :: Python :: 3.10
Classifier: Programming Language :: Python :: 3.11
Classifier: Programming Language :: Python :: 3.12
Classifier: Programming Language :: Python :: 3.13
Classifier: Programming Language :: Python :: 3.14
Classifier: Programming Language :: Python :: 3 :: Only
Classifier: Topic :: Software Development :: Libraries
Requires-Dist: nb_log>=13.9
Requires-Dist: nb_libs>=1.9
Requires-Dist: nb_time>=2.7
Requires-Dist: pymongo>=4.6.3
Requires-Dist: AMQPStorm==2.10.6
Requires-Dist: rabbitpy==2.0.1
Requires-Dist: decorator==5.1.1
Requires-Dist: tomorrow3==1.1.0
Requires-Dist: persist-queue>=0.4.2
Requires-Dist: apscheduler<4.0.0,>=3.10.1
Requires-Dist: pikav0
Requires-Dist: pikav1
Requires-Dist: redis2
Requires-Dist: redis3
Requires-Dist: redis5
Requires-Dist: redis
Requires-Dist: setuptools_rust
Requires-Dist: fabric2>=2.6.0
Requires-Dist: nb_filelock
Requires-Dist: pysnooper
Requires-Dist: deprecated
Requires-Dist: cryptography
Requires-Dist: auto_run_on_remote
Requires-Dist: frozenlist
Requires-Dist: fire
Requires-Dist: pydantic
Requires-Dist: orjson
Requires-Dist: async-timeout
Requires-Dist: typing-extensions
Provides-Extra: all
Requires-Dist: confluent_kafka==1.7.0; extra == "all"
Requires-Dist: pulsar-client==3.1.0; python_version >= "3.7" and extra == "all"
Requires-Dist: celery; extra == "all"
Requires-Dist: flower; extra == "all"
Requires-Dist: nameko==2.14.1; extra == "all"
Requires-Dist: sqlalchemy==1.4.13; extra == "all"
Requires-Dist: sqlalchemy_utils==0.36.1; extra == "all"
Requires-Dist: dramatiq==1.14.2; extra == "all"
Requires-Dist: huey==2.4.5; extra == "all"
Requires-Dist: rq==1.15.0; extra == "all"
Requires-Dist: kombu; extra == "all"
Requires-Dist: elasticsearch; extra == "all"
Requires-Dist: gnsq==1.0.1; extra == "all"
Requires-Dist: psutil; extra == "all"
Requires-Dist: peewee==3.17.3; extra == "all"
Requires-Dist: nats-python; extra == "all"
Requires-Dist: aiohttp==3.8.3; extra == "all"
Requires-Dist: paho-mqtt; extra == "all"
Requires-Dist: rocketmq; extra == "all"
Requires-Dist: zmq; extra == "all"
Requires-Dist: pyzmq; extra == "all"
Requires-Dist: kafka-python==2.0.2; extra == "all"
Requires-Dist: eventlet==0.33.3; extra == "all"
Requires-Dist: gevent==22.10.2; extra == "all"
Requires-Dist: mysql-replication==1.0.9; extra == "all"
Requires-Dist: grpcio==1.60.0; extra == "all"
Requires-Dist: grpcio-tools==1.60.0; extra == "all"
Requires-Dist: protobuf==4.25.1; extra == "all"
Requires-Dist: waitress; extra == "all"
Requires-Dist: flask; extra == "all"
Requires-Dist: flask_bootstrap; extra == "all"
Requires-Dist: flask_wtf; extra == "all"
Requires-Dist: wtforms; extra == "all"
Requires-Dist: flask_login; extra == "all"
Provides-Extra: extra-brokers
Requires-Dist: confluent_kafka==1.7.0; extra == "extra-brokers"
Requires-Dist: pulsar-client==3.1.0; python_version >= "3.7" and extra == "extra-brokers"
Requires-Dist: celery; extra == "extra-brokers"
Requires-Dist: flower; extra == "extra-brokers"
Requires-Dist: nameko==2.14.1; extra == "extra-brokers"
Requires-Dist: sqlalchemy==1.4.13; extra == "extra-brokers"
Requires-Dist: sqlalchemy_utils==0.36.1; extra == "extra-brokers"
Requires-Dist: dramatiq==1.14.2; extra == "extra-brokers"
Requires-Dist: huey==2.4.5; extra == "extra-brokers"
Requires-Dist: rq==1.15.0; extra == "extra-brokers"
Requires-Dist: kombu; extra == "extra-brokers"
Requires-Dist: elasticsearch; extra == "extra-brokers"
Requires-Dist: gnsq==1.0.1; extra == "extra-brokers"
Requires-Dist: psutil; extra == "extra-brokers"
Requires-Dist: peewee==3.17.3; extra == "extra-brokers"
Requires-Dist: nats-python; extra == "extra-brokers"
Requires-Dist: aiohttp==3.8.3; extra == "extra-brokers"
Requires-Dist: paho-mqtt; extra == "extra-brokers"
Requires-Dist: rocketmq; extra == "extra-brokers"
Requires-Dist: zmq; extra == "extra-brokers"
Requires-Dist: pyzmq; extra == "extra-brokers"
Requires-Dist: kafka-python==2.0.2; extra == "extra-brokers"
Requires-Dist: eventlet==0.33.3; extra == "extra-brokers"
Requires-Dist: gevent==22.10.2; extra == "extra-brokers"
Requires-Dist: mysql-replication==1.0.9; extra == "extra-brokers"
Requires-Dist: grpcio==1.60.0; extra == "extra-brokers"
Requires-Dist: grpcio-tools==1.60.0; extra == "extra-brokers"
Requires-Dist: protobuf==4.25.1; extra == "extra-brokers"
Requires-Dist: waitress; extra == "extra-brokers"
Provides-Extra: flask
Requires-Dist: flask; extra == "flask"
Requires-Dist: flask_bootstrap; extra == "flask"
Requires-Dist: flask_wtf; extra == "flask"
Requires-Dist: wtforms; extra == "flask"
Requires-Dist: flask_login; extra == "flask"
Dynamic: author
Dynamic: author-email
Dynamic: classifier
Dynamic: description
Dynamic: description-content-type
Dynamic: home-page
Dynamic: keywords
Dynamic: license
Dynamic: maintainer
Dynamic: maintainer-email
Dynamic: platform
Dynamic: provides-extra
Dynamic: requires-dist
Dynamic: summary
